wscikit/__init__.py
wscikit/importnp.py
wscikit/adjust/__init__.py
wscikit/adjust/ref.py
wscikit/compute/__init__.py
wscikit/compute/csd.py
wscikit-0.0.3.dist-info/LICENSE
wscikit-0.0.3.dist-info/METADATA
wscikit-0.0.3.dist-info/WHEEL
wscikit-0.0.3.dist-info/top_level.txt
wscikit-0.0.3.dist-info/RECORD
