Metadata-Version: 2.1
Name: wscikit
Version: 0.0.3
Summary: Westerberg Science Toolkit for Electrophysiology
Home-page: https://github.com/westerberg-science/wscikit
Author: Jacob A. Westerberg
Author-email: jakewesterberg@gmail.com
License: UNKNOWN
Project-URL: Bug Tracker, https://github.com/westerberg-science/wscikit/issues
Platform: UNKNOWN
Classifier: Programming Language :: Python :: 3
Classifier: License :: OSI Approved :: MIT License
Classifier: Operating System :: OS Independent
Requires-Python: >=3.6
License-File: LICENSE
